bolinette/api/README.md
bolinette/api/__init__.py
bolinette/api/autoroute.py
bolinette/api/controller.py
bolinette/api/extension.py
bolinette/api/py.typed
bolinette/api/pyproject.toml
bolinette_api-0.18.2.dist-info/LICENSE.txt
bolinette_api-0.18.2.dist-info/METADATA
bolinette_api-0.18.2.dist-info/WHEEL
bolinette_api-0.18.2.dist-info/RECORD
